pdf_task/__init__.py
pdf_task/main.py
pdf_task/pdf_handler.py
pdf_task2/__init__.py
pdf_task2/main.py
pdf_task2/pdf_handler.py
wangwangwang_pypi_test-1.0.0.dist-info/LICENSE
wangwangwang_pypi_test-1.0.0.dist-info/METADATA
wangwangwang_pypi_test-1.0.0.dist-info/WHEEL
wangwangwang_pypi_test-1.0.0.dist-info/top_level.txt
wangwangwang_pypi_test-1.0.0.dist-info/RECORD
