Metadata-Version: 2.1
Name: wangwangwang-pypi-test
Version: 1.0.0
Summary: pypi测试
Home-page: https://github.com/test
Author: wangxiaoxi
Author-email: 1046474088@qq.com
License: MIT
Classifier: License :: OSI Approved :: MIT License
Classifier: Operating System :: OS Independent
Classifier: Programming Language :: Python :: 3
Requires-Python: >=3.8
License-File: LICENSE
Requires-Dist: pdfplumber (==0.8.0)
Requires-Dist: PyPDF2 (==3.0.1)
Requires-Dist: setuptools (==67.3.3)
